nonebot_plugin_gemini-0.5.1.dist-info/METADATA
nonebot_plugin_gemini-0.5.1.dist-info/WHEEL
nonebot_plugin_gemini-0.5.1.dist-info/entry_points.txt
nonebot_plugin_gemini-0.5.1.dist-info/licenses/LICENSE
nonebot_plugin_gemini/__init__.py
nonebot_plugin_gemini/config.py
nonebot_plugin_gemini/search_engines/__init__.py
nonebot_plugin_gemini/search_engines/google/__init__.py
nonebot_plugin_gemini/search_engines/google/models.py
nonebot_plugin_gemini/search_engines/models.py
nonebot_plugin_gemini-0.5.1.dist-info/RECORD
