Metadata-Version: 2.1
Name: nonebot-plugin-gemini
Version: 0.5.1
Summary: ✨ Gemini AI 对话 NoneBot 插件 ✨
Author-Email: zhaomaoniu <2667292003@qq.com>
License: MIT
Requires-Python: >=3.9
Requires-Dist: nonebot2>=2.1.3
Requires-Dist: nonebot-plugin-alconna>=0.35.1
Requires-Dist: nonebot-plugin-htmlrender>=0.2.3
Requires-Dist: aiohttp>=3.9.1
Requires-Dist: fleep>=1.0.1
Requires-Dist: google-generativeai>=0.4.1
Requires-Dist: nonebot-plugin-uninfo>=0.6.2
